HISTORY.rst
LICENSE
MANIFEST.in
README.rst
requirements-docs.txt
requirements-tests.txt
requirements.txt
setup.py
restgate/__init__.py
restgate/exceptions.py
restgate.egg-info/PKG-INFO
restgate.egg-info/SOURCES.txt
restgate.egg-info/dependency_links.txt
restgate.egg-info/not-zip-safe
restgate.egg-info/requires.txt
restgate.egg-info/top_level.txt