Metadata-Version: 1.1
Name: restgate
Version: 0.1.3
Summary: Library for using a RESTful API hosted on AWS API Gateway
Home-page: https://github.com/cloudnative/restgate-py
Author: Peter Sankauskas
Author-email: info@cloudnative.io
License: Apache License, Version 2.0
Platform: UNKNOWN
Classifier: Development Status :: 3 - Alpha
Classifier: Intended Audience :: Developers
Classifier: License :: OSI Approved :: Apache Software License
Classifier: Natural Language :: English
Classifier: Programming Language :: Python
Classifier: Programming Language :: Python :: 2.7
Classifier: Programming Language :: Python :: 3.5
